main.py
setup.py
pyyal.egg-info/PKG-INFO
pyyal.egg-info/SOURCES.txt
pyyal.egg-info/dependency_links.txt
pyyal.egg-info/requires.txt
pyyal.egg-info/top_level.txt